motoevsentiment/__init__.py
motoevsentiment/wsentiment/__init__.py
motoevsentiment/wsentiment/whatsappdataframe.py
motoevsentiment/wsentiment/whatsappsentiment.py
sentiment_package-0.1.1.dist-info/METADATA
sentiment_package-0.1.1.dist-info/WHEEL
sentiment_package-0.1.1.dist-info/top_level.txt
sentiment_package-0.1.1.dist-info/RECORD
