Metadata-Version: 2.4
Name: sentiment-package
Version: 0.1.1
Summary: Package to analyse Motorcycle EV swap related issues
Author: Ayikwei Richard
Requires-Python: >=3.11
Requires-Dist: pandas>=2.3.1
Requires-Dist: pytest>=8.4.1
Requires-Dist: setuptools>=80.9.0
Requires-Dist: twine>=6.1.0
Dynamic: author
